LICENSE
MANIFEST.in
README.md
requirements.txt
setup.cfg
setup.py
mlx_diffusion/__init__.py
mlx_diffusion/image2image.py
mlx_diffusion/txt2image.py
mlx_diffusion.egg-info/PKG-INFO
mlx_diffusion.egg-info/SOURCES.txt
mlx_diffusion.egg-info/dependency_links.txt
mlx_diffusion.egg-info/requires.txt
mlx_diffusion.egg-info/top_level.txt
mlx_diffusion/stable_diffusion/__init__.py
mlx_diffusion/stable_diffusion/clip.py
mlx_diffusion/stable_diffusion/config.py
mlx_diffusion/stable_diffusion/model_io.py
mlx_diffusion/stable_diffusion/sampler.py
mlx_diffusion/stable_diffusion/tokenizer.py
mlx_diffusion/stable_diffusion/unet.py
mlx_diffusion/stable_diffusion/vae.py