Metadata-Version: 2.1
Name: mlx-diffusion
Version: 0.0.1
Summary: Mlx-Diffusion
Home-page: https://github.com/kadirnar/mlx-diffusion
Author: kadirnar
Author-email: kadir.nar@hotmail.com
License: Apache License 2.0
License-File: LICENSE
